{
  "schema_version": "factual_enrichment/v1",
  "generated_at_utc": "2026-04-05T21:10:29.733499+00:00",
  "account_id": "acc_6bb4cbb1a3e4",
  "source_file": "Sydney 100.csv",
  "source_bundle_ref": "outputs/source_bundles/Sydney 100/acc_6bb4cbb1a3e4.json",
  "identity": {
    "hotel_name": "Seranin | Gordon",
    "city": "Gordon",
    "state": "New South Wales",
    "country_code": "AU",
    "hotel_type_class": "Preferred hotel",
    "category_name": "Motel",
    "ownership_type": "Independent operator candidate",
    "google_place_name": "",
    "google_primary_type": "",
    "google_primary_type_display_name": "",
    "google_types": []
  },
  "contacts": {
    "website": "http://www.seranin.com.au/",
    "website_domain": "seranin.com.au",
    "phone": "+61 1300 821 332",
    "source_origin": "processed_row"
  },
  "address": {
    "street": "807 Pacific Hwy",
    "city": "Gordon",
    "state": "New South Wales",
    "country_code": "AU",
    "formatted": "807 Pacific Hwy, Gordon, New South Wales, AU",
    "source_origin": "processed_row"
  },
  "operating_hours": {
    "hotel_opening_hours": "Verejne nepotvrdené",
    "status": "Verejne nepotvrdené",
    "source_url": "",
    "source_type": "",
    "google_places_weekday_text": ""
  },
  "checkin_checkout": {
    "value": "Verejne nepotvrdené",
    "status": "Verejne nepotvrdené",
    "source_url": "",
    "source_type": "",
    "source_origin": "",
    "completeness": "none"
  },
  "room_count_signal": {
    "value": "",
    "rooms_range": "",
    "status": "Verejne nepotvrdené",
    "source_origin": "",
    "note": "Presný počet izieb je verejne nepotvrdený v aktuálnom source bundle."
  },
  "service_mix": {
    "wellness": {
      "available": "unknown",
      "source_origin": "",
      "evidence": "Verejne nepotvrdené"
    },
    "restaurant": {
      "available": "unknown",
      "source_origin": "",
      "evidence": "Verejne nepotvrdené"
    },
    "event_congress": {
      "available": "unknown",
      "source_origin": "",
      "evidence": "Verejne nepotvrdené"
    },
    "spa": {
      "available": "unknown",
      "source_origin": "",
      "evidence": "Verejne nepotvrdené"
    },
    "parking": {
      "available": "unknown",
      "source_origin": "",
      "evidence": "Verejne nepotvrdené"
    },
    "bowling": {
      "available": "unknown",
      "source_origin": "",
      "evidence": "Verejne nepotvrdené"
    }
  },
  "review_trust_signal": {
    "summary": "3.5/5 z 65 recenzií",
    "score": "3.5",
    "reviews_count": "65",
    "status": "raw_confirmed",
    "source_origin": "processed_row"
  },
  "google_review_signal": {
    "rating": "",
    "user_ratings_total": "",
    "status": "Verejne nepotvrdené",
    "source_origin": ""
  },
  "ownership_company_signal": {
    "value": "Seranin Group",
    "status": "public_confirmed",
    "source_origin": "official_web_jsonld",
    "note": "JSON-LD názov: Seranin Group | typ: localbusiness"
  },
  "source_reachability": {
    "public_source_reachable": "yes",
    "public_source_fetch_status": "ok",
    "google_places_status": "not_enabled"
  }
}